{"id":"MN2XQGUVQDFRZ","name":"ConnectToRemoteServer","size":1163,"btime":1773192045484,"mtime":1643875318000,"ext":"svg","tags":[],"folders":["MN2XQGU4R4E9A"],"isDeleted":false,"url":"","annotation":"","modificationTime":1774255199124,"removeThumbnail":true,"noThumbnail":true,"height":16,"width":16,"lastModified":1774255451136,"palettes":[{"color":[36,36,36],"ratio":59},{"color":[4,100,91],"ratio":27},{"color":[28,132,35],"ratio":5},{"color":[4,108,87],"ratio":3.39},{"color":[36,124,36],"ratio":1.64},{"color":[12,100,84],"ratio":1.18},{"color":[28,28,28],"ratio":0.53},{"color":[44,124,38],"ratio":0.34}]}