{"id":"MN2XQGUVAXTR1","name":"CSClassFile","size":1044,"btime":1773192046267,"mtime":1643875326000,"ext":"svg","tags":[],"folders":["MN2XQGU4R4E9A"],"isDeleted":false,"url":"","annotation":"","modificationTime":1774255199243,"removeThumbnail":true,"noThumbnail":true,"height":16,"width":16,"lastModified":1774255449827,"palettes":[{"color":[36,36,36],"ratio":58},{"color":[27,132,35],"ratio":35},{"color":[37,124,34],"ratio":1.83},{"color":[28,28,28],"ratio":1.83},{"color":[36,132,30],"ratio":1.83}]}